image_package/__init__.py
image_processing_package_robelio-0.1.0.dist-info/licenses/LICENSE.md
image_processing_package_robelio-0.1.0.dist-info/METADATA
image_processing_package_robelio-0.1.0.dist-info/WHEEL
image_processing_package_robelio-0.1.0.dist-info/top_level.txt
image_processing_package_robelio-0.1.0.dist-info/RECORD
