Metadata-Version: 2.4
Name: image-processing-package-robelio
Version: 0.1.0
Summary: Pacote para processamento de imagens
Home-page: https://github.com/robellio/image-processing-package
Author: Robélio Barreto
Author-email: Robélio Barreto <robeliobasantos@gmail.com>
License: MIT
Project-URL: Homepage, https://github.com/robellio/image-processing-package
Requires-Python: >=3.8
License-File: LICENSE.md
Requires-Dist: Pillow>=9.0.0
Requires-Dist: numpy>=1.21.0
Requires-Dist: matplotlib>=3.5.0
Dynamic: license-file
